fymail/__init__.py
fymail/error.py
fymail/fymail.py
fymail/provider_manager.py
fymail/providers/__init__.py
fymail/providers/base/__init__.py
fymail/providers/base/provider_base.py
fymail/providers/base/rule_base.py
fymail/providers/github/__init__.py
fymail/providers/github/github.py
fymail/providers/github/rules/__init__.py
fymail/providers/github/rules/commits.py
fymail/providers/github/rules/events.py
fymail/providers/github/rules/profile.py
fymail/providers/github/rules/users.py
fymail/utils/__init__.py
fymail/utils/collect.py
fymail-0.1.0.dist-info/METADATA
fymail-0.1.0.dist-info/WHEEL
fymail-0.1.0.dist-info/licenses/LICENSE.txt
fymail-0.1.0.dist-info/RECORD
